bw_sdk-0.1.12.dist-info/METADATA
bw_sdk-0.1.12.dist-info/WHEEL
bw_sdk/__init__.py
bw_sdk/model.py
bw_sdk/py.typed
bw_sdk-0.1.12.dist-info/RECORD
