Metadata-Version: 2.1
Name: bw-sdk
Version: 0.1.12
Author-Email: Kalle M. Aagaard <git@k-moeller.dk>
License: MIT
Project-URL: Repository, https://github.com/KalleDK/py-bitwarden-sdk
Requires-Python: >=3.12
Requires-Dist: httpx>=0.25.0
Requires-Dist: pydantic>=2.4.2
